{

"Figures":
	[
	   {
		"Point A": {"coord x": 45,"coord y": 6},
		"Point B": {"coord x": 432,"coord y": 6},
		"Point C": {"coord x": 43,"coord y": 6},
		"Point D": {"coord x": 34,"coord y": 7}
			   },
	   {
		"Point A": {"coord x": 654,"coord y": 67},
		"Point B": {"coord x": 234,"coord y": 7},
		"Point C": {"coord x": 7,"coord y": 45},
		"Point D": {"coord x": 6,"coord y": 75}
			   },
	   {
		"Point A": {"coord x": 45,"coord y": 57},
		"Point B": {"coord x": 43,"coord y": 6},
		"Point C": {"coord x": 7,"coord y": 8},
		"Point D": {"coord x": 5,"coord y": 3}
			   }
	],
	   "size": 10 ,
	   "current size" : 3
}
